cli_mcpx/__init__.py
cli_mcpx/__main__.py
cli_mcpx/cli.py
cli_mcpx/commands/__init__.py
cli_mcpx-2.0.1.dist-info/METADATA
cli_mcpx-2.0.1.dist-info/WHEEL
cli_mcpx-2.0.1.dist-info/entry_points.txt
cli_mcpx-2.0.1.dist-info/licenses/LICENSE
cli_mcpx-2.0.1.dist-info/RECORD
