Metadata-Version: 2.4
Name: cli-mcpx
Version: 2.0.1
Summary: A modern Python CLI tool for MCP (Model Context Protocol) server management
Author-email: Kang Hee Yong <cagojeiger@naver.com>
License-File: LICENSE
Keywords: cli,mcp,model-context-protocol,tool
Classifier: Development Status :: 3 - Alpha
Classifier: Environment :: Console
Classifier: Intended Audience :: Developers
Classifier: License :: OSI Approved :: MIT License
Classifier: Programming Language :: Python :: 3
Classifier: Programming Language :: Python :: 3.11
Classifier: Programming Language :: Python :: 3.12
Classifier: Topic :: Software Development :: Libraries :: Application Frameworks
Classifier: Topic :: Utilities
Requires-Python: >=3.11
Requires-Dist: typer>=0.16.0
